[
    {
        "name": "Volatile_Objects_Without_Address_Clauses",
        "path": "volatileObjectsWithoutAddressClauses.lkql",
        "params": []
    },

    {
        "name": "Specific_Pre_Post",
        "path": "specific_pre_post.lkql",
        "params": []
    },

    {
        "name": "Implicit_Small",
        "path": "implicit_small.lkql",
        "params": []
    },

    {
        "name": "Too_Many_Primitives",
        "path": "too_many_primitives.lkql",
        "params": [
            {
                "name": "n",
                "type": "int",
                "default": 3
            }
        ]
    },

    {
        "name": "Deep_Library_Hierarchy",
        "path": "deep_library_hierarchy.lkql",
        "params": [
            {
                "name": "depth",
                "type": "int",
                "default": 5
            }
        ]
    },

    {
        "name": "Raising_Predefined_Exceptions",
        "path": "raising_predefined_exceptions.lkql",
        "params": []
    },

    {
        "name": "No_Explicit_Real_Range",
        "path": "no_real_range.lkql",
        "params": []
    },

    {
        "name": "Deep_Inheritance",
        "path": "deepInheritance.lkql",
        "params": [
            {
                "name": "depth",
                "type": "int",
                "default": 2
            }
        ]
    },

    {
        "name": "Multiple_Entries",
        "path": "multipleEntries.lkql",
        "params": []
    },

    {
        "name": "GOTO_Statements",
        "path": "gotoStatements.lkql",
        "params": []
    }
]
